setup.py
restxl/__init__.py
restxl/base.py
restxl/client.py
restxl/computations.py
restxl/exceptions.py
restxl/headers.py
restxl/path_variables.py
restxl/request.py
restxl/url_variables.py
restxl/validators.py
restxl.egg-info/PKG-INFO
restxl.egg-info/SOURCES.txt
restxl.egg-info/dependency_links.txt
restxl.egg-info/not-zip-safe
restxl.egg-info/requires.txt
restxl.egg-info/top_level.txt
restxl/tests/__init__.py
restxl/tests/cloudfiles/__init__.py
restxl/tests/cloudfiles/auth_requests.py
restxl/tests/cloudfiles/cdn_requests.py
restxl/tests/cloudfiles/cloudfiles_requests.py
restxl/tests/cloudfiles/storage_requests.py
restxl/tests/cloudfiles/test_settings.py
restxl/tests/gmaps/__init__.py
restxl/tests/gmaps/client.py
restxl/tests/gmaps/requests.py
restxl/tests/gmaps/tests.py